modfin/__init__.py
modfin/Backtest/__init__.py
modfin/Backtest/base.py
modfin/analysis/__init__.py
modfin/analysis/return_analysis.py
modfin/analysis/risk_matrix.py
modfin/metrics/__init__.py
modfin/metrics/ratio_metrics.py
modfin/metrics/return_metrics.py
modfin/metrics/risk_metrics.py
modfin/numba_funcs/__init__.py
modfin/numba_funcs/nb_ratio_metrics.py
modfin/numba_funcs/nb_series.py
modfin/portfolio_opt/__init__.py
modfin/portfolio_opt/base.py
modfin/portfolio_opt/ewp.py
modfin/portfolio_opt/hrp.py
modfin/portfolio_opt/ivp.py
modfin/portfolio_opt/rkp.py
modfin/utils/__init__.py
modfin/utils/portifolioopt_tools.py
modfin/utils/riskmatrix_tools.py
modfin/utils/series_tools.py
modfin-0.1.5.dist-info/LICENSE
modfin-0.1.5.dist-info/METADATA
modfin-0.1.5.dist-info/WHEEL
modfin-0.1.5.dist-info/top_level.txt
modfin-0.1.5.dist-info/RECORD
