Metadata-Version: 2.1
Name: modfin
Version: 0.1.5
Summary: Modules for Quantitative Financial Analysis
Home-page: https://github.com/GabrielAbra/modfin
Author: Gabriel Abrahao
Author-email: gabrielabrahaorr@gmail.com
License: MIT
Project-URL: Bug Tracker, https://github.com/GabrielAbra/modfin/issues
Classifier: License :: OSI Approved :: MIT License
Classifier: Programming Language :: Python :: 3
Classifier: Programming Language :: Python :: 3.8
Classifier: Programming Language :: Python :: 3.9
Classifier: Programming Language :: Python :: Implementation :: CPython
Classifier: Programming Language :: Python :: Implementation :: PyPy
Classifier: Topic :: Office/Business :: Financial :: Investment
Requires-Python: >=3.8
License-File: LICENSE
Requires-Dist: numpy
Requires-Dist: pandas
Requires-Dist: scipy
Requires-Dist: matplotlib
Requires-Dist: scikit-learn
Requires-Dist: numba
